setup.py
llm_datatech/__init__.py
llm_datatech/llm_datatech.py
llm_datatech.egg-info/PKG-INFO
llm_datatech.egg-info/SOURCES.txt
llm_datatech.egg-info/dependency_links.txt
llm_datatech.egg-info/top_level.txt