Metadata-Version: 2.1
Name: llm-datatech
Version: 0.1.0
Summary: RAG llm datatech
Author: datatech
Author-email: tdf@totalenergies.com
Classifier: Programming Language :: Python :: 3
Classifier: License :: OSI Approved :: MIT License
Classifier: Operating System :: OS Independent
Requires-Python: >=3.6
